video_sweep/classifier.py
video_sweep/cli.py
video_sweep/finder.py
video_sweep/renamer.py
video_sweep/utils.py
video_sweep-0.1.0.dist-info/licenses/LICENSE
video_sweep-0.1.0.dist-info/METADATA
video_sweep-0.1.0.dist-info/WHEEL
video_sweep-0.1.0.dist-info/entry_points.txt
video_sweep-0.1.0.dist-info/top_level.txt
video_sweep-0.1.0.dist-info/RECORD
