Metadata-Version: 2.4
Name: video-sweep
Version: 0.1.0
Summary: Minimal CLI tool to find, classify, rename, and move video files.
Author-email: Colin Brown <colinmakerofthings@gmail.com>
License-Expression: MIT
Requires-Python: >=3.8
License-File: LICENSE
Requires-Dist: tomli; python_version < "3.11"
Dynamic: license-file
